peotry_demo/#fibo.py#
peotry_demo/__init__.py
peotry_demo/fibo.py
peotry_demo/hello.py
peotry_demo-3.2.4.dist-info/WHEEL
peotry_demo-3.2.4.dist-info/METADATA
peotry_demo-3.2.4.dist-info/RECORD
